dj_pony/applied_migrations_checker/__init__.py
dj_pony/applied_migrations_checker/apps.py
dj_pony/applied_migrations_checker/management/__init__.py
dj_pony/applied_migrations_checker/management/commands/__init__.py
dj_pony/applied_migrations_checker/management/commands/applied_migrations_checker.py
dj_pony.applied_migrations_checker-0.1.4.dist-info/LICENSE
dj_pony.applied_migrations_checker-0.1.4.dist-info/WHEEL
dj_pony.applied_migrations_checker-0.1.4.dist-info/METADATA
dj_pony.applied_migrations_checker-0.1.4.dist-info/RECORD
