Metadata-Version: 2.1
Name: dj-pony.applied-migrations-checker
Version: 0.1.4
Summary: Check that all django database migrations have been applied.
License: MIT
Author: Samuel Bishop
Author-email: sam@techdragon.io
Requires-Python: >=3.6,<4.0
Classifier: License :: OSI Approved :: MIT License
Classifier: Programming Language :: Python :: 3
Classifier: Programming Language :: Python :: 3.6
Classifier: Programming Language :: Python :: 3.7
Classifier: Programming Language :: Python :: 3.8
Classifier: Programming Language :: Python :: 3.9
Requires-Dist: django (>=1.8)
